cp2k_tools/__init__.py
cp2k_tools/cli.py
cp2k_tools/tools.py
cp2k_tools/generator/__init__.py
cp2k_tools/generator/cli.py
cp2k_tools/generator/input.py
cp2k_tools/generator/xyz.py
cp2k_tools/parser/__init__.py
cp2k_tools/parser/input.py
cp2k_tools/parser/input_cli.py
cp2k_tools/parser/output.py
cp2k_tools/parser/xyz.py
cp2k_tools/parser/xyz_cli.py
cp2k_tools-0.0.9.data/scripts/cp2k_bs2csv.py
cp2k_tools-0.0.9.data/scripts/cp2k_pdos.py
tests/__init__.py
tests/input_parser_test.py
tests/xyz_cli_test.py
tests/xyz_parser_test.py
cp2k_tools-0.0.9.dist-info/LICENSE
cp2k_tools-0.0.9.dist-info/METADATA
cp2k_tools-0.0.9.dist-info/WHEEL
cp2k_tools-0.0.9.dist-info/entry_points.txt
cp2k_tools-0.0.9.dist-info/top_level.txt
cp2k_tools-0.0.9.dist-info/RECORD
