Metadata-Version: 2.1
Name: cp2k-tools
Version: 0.0.9
Summary: CP2K tools & scripts
Home-page: http://github.com/dev-zero/cp2k-tools
Author: Tiziano Müller
Author-email: tiziano.mueller@chem.uzh.ch
License: GPL3
Platform: UNKNOWN
Classifier: Development Status :: 4 - Beta
Classifier: Environment :: Console
Classifier: Intended Audience :: Developers
Classifier: License :: OSI Approved :: Apache Software License
Classifier: Operating System :: POSIX
Classifier: Programming Language :: Python
Requires-Dist: setuptools
Requires-Dist: docopt
Requires-Dist: numpy
Requires-Dist: parsimonious (>=0.8)
Requires-Dist: click (>=6.7)
Requires-Dist: regex (>=2017.09.23)
